<?xml version="1.0" encoding="utf-8"?>
<!--Test Level-->
<ItemCollection>
  <Items>

  	 <!-- PLAYER -->
    <Item type ="3">
      <posX>7.2</posX>
      <posY>-4.0</posY>
    </Item>

  	<!-- WALLS -->
  	<Item type ="12">
      <posX>0.3</posX>
      <posY>-2.51</posY>
    </Item>
    <Item type ="12">
      <posX>0.5</posX>
      <posY>-2.51</posY>
    </Item>

    <!-- BACKGROUND -->
  	<Item type ="11">
      <posX>-0.01</posX>
      <posY>-0.04</posY>
    </Item> 

    <!-- FLOATING PLATFORMS -->
   	<Item type ="23">
      <posX>-5.5</posX>
      <posY>-0.26</posY>
    </Item> 
     <Item type ="22">
      <posX>2.5</posX>
      <posY>-0.26</posY>
    </Item> 

    <!-- PILLAR -->
    <Item type ="17">
      <posX>-1.2</posX>
      <posY>-2.51</posY>
    </Item>

    <!-- FRIEND BOT -->
    <Item type ="21">
      <posX>-0.66</posX>
      <posY>-2.6</posY>
    </Item>

    <!-- ENEMIES -->
    <Item type ="4">
      <posX>-5.0</posX>
      <posY>-4.15</posY>
    </Item>
    <Item type ="4">
      <posX>2.5</posX>
      <posY>-4.15</posY>
    </Item>
    <Item type ="4">
      <posX>-7.35</posX>
      <posY>1.87</posY>
    </Item>
     <Item type ="4">
      <posX>4.7</posX>
      <posY>1.87</posY>
    </Item>

     <Item type ="5">
      <posX>-1.2</posX>
      <posY>1.86</posY>
    </Item>
    <Item type ="26">
      <posX>0</posX>
      <posY>0</posY>
    </Item>

    <!-- ITEMS -->
     <Item type ="7">
      <posX>0.0</posX>
      <posY>3.0</posY>
    </Item>
     <Item type ="7">
      <posX>7.2</posX>
      <posY>3.6</posY>
    </Item>

    <!-- BUTTONS -->
     <Item type ="18">
      <posX>0.0</posX>
      <posY>-4.1</posY>
    </Item>
    <Item type ="19">
      <posX>0.0</posX>
      <posY>4.42</posY>
    </Item>




  	<!-- DOORS -->
  	<Item type ="10">
      <posX>-7.2</posX>
      <posY>3.51</posY>
    </Item>
     <Item type ="9">
      <posX>7.23</posX>
      <posY>-4</posY>
    </Item>

 	<!-- FLOOR -->
    <Item type ="0">
      <posX>-7.2</posX>
      <posY>-4.76</posY>
    </Item>
    <Item type ="0">
      <posX>-6.2</posX>
      <posY>-4.76</posY>
    </Item>
    <Item type ="0">
      <posX>-5.2</posX>
      <posY>-4.76</posY>
    </Item>
    <Item type ="0">
      <posX>-4.2</posX>
      <posY>-4.76</posY>
    </Item>
    <Item type ="0">
      <posX>-3.2</posX>
      <posY>-4.76</posY>
    </Item>
    <Item type ="0">
      <posX>-2.2</posX>
      <posY>-4.76</posY>
    </Item>
    <Item type ="0">
      <posX>-1.2</posX>
      <posY>-4.76</posY>
    </Item>
    <Item type ="0">
      <posX>-0.2</posX>
      <posY>-4.76</posY>
    </Item>
    <Item type ="0">
      <posX>0.8</posX>
      <posY>-4.76</posY>
    </Item>
    <Item type ="0">
      <posX>1.8</posX>
      <posY>-4.76</posY>
    </Item>
    <Item type ="0">
      <posX>2.8</posX>
      <posY>-4.76</posY>
    </Item>
    <Item type ="0">
      <posX>3.8</posX>
      <posY>-4.76</posY>
    </Item>
    <Item type ="0">
      <posX>4.8</posX>
      <posY>-4.76</posY>
    </Item>
    <Item type ="0">
      <posX>5.8</posX>
      <posY>-4.76</posY>
    </Item>
    <Item type ="0">
      <posX>6.8</posX>
      <posY>-4.76</posY>
    </Item>
    <Item type ="0">
      <posX>7.8</posX>
      <posY>-4.76</posY>
    </Item>

    <!-- PLATFORMS -->

    <Item type ="1">
      <posX>-7.2</posX>
      <posY>-3.26</posY>
    </Item>
     <Item type ="0">
      <posX>-6.2</posX>
      <posY>-3.26</posY>
    </Item>
     <Item type ="0">
      <posX>-5.2</posX>
      <posY>-3.26</posY>
    </Item>
    <Item type ="0">
      <posX>-3.2</posX>
      <posY>-3.26</posY>
    </Item>

	<Item type ="1">
      <posX>-1.5</posX>
      <posY>3.26</posY>
    </Item>
    <Item type ="1">
      <posX>1.5</posX>
      <posY>3.26</posY>
    </Item>

    <Item type ="0">
      <posX>-2.5</posX>
      <posY>2.76</posY>
    </Item>
    <Item type ="0">
      <posX>2.5</posX>
      <posY>2.76</posY>
    </Item>

      <Item type ="0">
      <posX>-2.2</posX>
      <posY>-3.26</posY>
    </Item>
     <Item type ="0">
      <posX>-1.2</posX>
      <posY>-3.26</posY>
    </Item>
       <Item type ="0">
      <posX>-0.2</posX>
      <posY>-3.26</posY>
    </Item>

     <Item type ="0">
      <posX>-7.2</posX>
      <posY>1.26</posY>
     </Item>
       <Item type ="0">
      <posX>-6.2</posX>
      <posY>1.26</posY>
     </Item>
     <Item type ="0">
      <posX>-5.2</posX>
      <posY>1.26</posY>
     </Item>
     <Item type ="0">
     <posX>-3.2</posX>
      <posY>1.26</posY>
     </Item>
      <Item type ="0">
     <posX>-2.2</posX>
      <posY>1.26</posY>
     </Item>
     <Item type ="0">
     <posX>-1.2</posX>
      <posY>1.26</posY>
     </Item>
     <Item type ="0">
     <posX>-0.2</posX>
      <posY>1.26</posY>
     </Item>
    <Item type ="1">
      <posX>-5.2</posX>
      <posY>-1.76</posY>
    </Item>
    <Item type ="0">
      <posX>-4.2</posX>
      <posY>-1.76</posY>
    </Item>
    <Item type ="0">
      <posX>-3.2</posX>
      <posY>-1.76</posY>
    </Item>
    <Item type ="1">
      <posX>-2.2</posX>
      <posY>-1.76</posY>
    </Item>
    <Item type ="0">
      <posX>-1.2</posX>
      <posY>-1.76</posY>
    </Item>
    <Item type ="0">
      <posX>-0.2</posX>
      <posY>-1.76</posY>
    </Item>
    <Item type ="0">
      <posX>-0.2</posX>
      <posY>-1.76</posY>
    </Item>
    <Item type ="0">
      <posX>0.8</posX>
      <posY>-1.76</posY>
    </Item>
	 <Item type ="1">
      <posX>1.8</posX>
      <posY>-1.76</posY>
    </Item>
     <Item type ="0">
      <posX>2.8</posX>
      <posY>-1.76</posY>
    </Item>
     <Item type ="0">
      <posX>3.8</posX>
      <posY>-1.76</posY>
    </Item>

     <Item type ="0">
      <posX>-7.2</posX>
      <posY>-1.76</posY>
    </Item>
      <Item type ="0">
      <posX>-7.2</posX>
      <posY>2.76</posY>
    </Item>
      <Item type ="0">
      <posX>-0.5</posX>
      <posY>3.76</posY>
    </Item>
    <Item type ="0">
      <posX>0.5</posX>
      <posY>3.76</posY>
    </Item>
      <Item type ="0">
      <posX>0.8</posX>
      <posY>-3.26</posY>
    </Item>
    <Item type ="0">
      <posX>1.8</posX>
      <posY>-3.26</posY>
    </Item>
    <Item type ="0">
      <posX>4.8</posX>
      <posY>1.26</posY>
    </Item>
     <Item type ="0">
      <posX>2.8</posX>
      <posY>1.26</posY>
    </Item>
     <Item type ="0">
      <posX>4.8</posX>
      <posY>-3.26</posY>
    </Item>
      <Item type ="0">
      <posX>5.8</posX>
      <posY>-3.26</posY>
    </Item>
      <Item type ="0">
      <posX>6.8</posX>
      <posY>-3.26</posY>
    </Item>
      <Item type ="0">
      <posX>7.8</posX>
      <posY>-3.26</posY>
    </Item>
    <Item type ="0">
      <posX>2.8</posX>
      <posY>-3.26</posY>
    </Item>
      <Item type ="1">
      <posX>4.8</posX>
      <posY>-1.76</posY>
    </Item>
      <Item type ="0">
      <posX>6.8</posX>
      <posY>-1.76</posY>
    </Item>
      <Item type ="0">
      <posX>7.8</posX>
      <posY>-1.76</posY>
    </Item>

    <Item type ="0">
      <posX>5.8</posX>
      <posY>1.26</posY>
    </Item>
      <Item type ="0">
      <posX>6.8</posX>
      <posY>1.26</posY>
    </Item>
      <Item type ="0">
      <posX>7.8</posX>
      <posY>1.26</posY>
    </Item>
      <Item type ="0">
      <posX>6.8</posX>
      <posY>2.76</posY>
    </Item>
      <Item type ="0">
      <posX>5.8</posX>
      <posY>2.76</posY>
    </Item>
       <Item type ="0">
      <posX>7.8</posX>
      <posY>2.76</posY>
    </Item>
      <Item type ="1">
      <posX>0.8</posX>
      <posY>1.26</posY>
    </Item>
    <Item type ="0">
      <posX>1.8</posX>
      <posY>1.26</posY>
    </Item>
  </Items>
</ItemCollection>
  